trakcli/__init__.py
trakcli/__main__.py
trakcli/callbacks.py
trakcli/config/__init__.py
trakcli/config/commands.py
trakcli/config/main.py
trakcli/config/models.py
trakcli/create/__init__.py
trakcli/create/commands/__init__.py
trakcli/create/commands/project.py
trakcli/create/commands/session.py
trakcli/create/commands/work.py
trakcli/create/create_sessions_methods.py
trakcli/create/messages/print_missing_duration.py
trakcli/create/messages/print_missing_timings_error.py
trakcli/create/messages/print_new_created_session.py
trakcli/database/__init__.py
trakcli/database/basic.py
trakcli/database/database.py
trakcli/database/models.py
trakcli/dev/__init__.py
trakcli/dev/commands.py
trakcli/initialize.py
trakcli/main.py
trakcli/projects/__init__.py
trakcli/projects/commands/__init__.py
trakcli/projects/commands/archive.py
trakcli/projects/commands/delete.py
trakcli/projects/commands/list.py
trakcli/projects/database.py
trakcli/projects/messages/print_project_archived_toggle.py
trakcli/projects/messages/print_project_broken_configuration.py
trakcli/projects/utils/__init__.py
trakcli/projects/utils/print_missing_project.py
trakcli/projects/utils/print_no_projects.py
trakcli/report/__init__.py
trakcli/report/commands/__init__.py
trakcli/report/commands/report_project.py
trakcli/report/functions/create_details_table.py
trakcli/report/functions/filter_records.py
trakcli/report/functions/get_grouped_records.py
trakcli/report/functions/get_table_title.py
trakcli/report/functions/test_functions.py
trakcli/tracker/__init__.py
trakcli/tracker/commands/get_current_session_status.py
trakcli/tracker/commands/start_tracker.py
trakcli/tracker/commands/stop_tracker.py
trakcli/tracker/messages/__init__.py
trakcli/tracker/messages/print_session_already_started.py
trakcli/utils/__init__.py
trakcli/utils/file_system/__init__.py
trakcli/utils/file_system/get_json_file_content.py
trakcli/utils/format_date.py
trakcli/utils/print_with_padding.py
trakcli/utils/same_week.py
trakcli-0.0.5.dist-info/METADATA
trakcli-0.0.5.dist-info/WHEEL
trakcli-0.0.5.dist-info/entry_points.txt
trakcli-0.0.5.dist-info/RECORD
