Metadata-Version: 2.1
Name: trakcli
Version: 0.0.5
Summary: Keep a record of the time you dedicate to your projects.
Home-page: https://usetrak.com/
License: AGPL-3.0
Keywords: cli,timetraker,time,traker,tool
Author: Luca Fedrizzi
Author-email: 9001053+fedriz@users.noreply.github.com
Requires-Python: >=3.11,<4.0
Classifier: License :: OSI Approved :: GNU Affero General Public License v3
Classifier: Programming Language :: Python :: 3
Classifier: Programming Language :: Python :: 3.11
Classifier: Programming Language :: Python :: 3.12
Requires-Dist: typer[all] (>=0.9.0)
Project-URL: Luca Fedrizzi's website, https://lucafedrizzi.com/
Project-URL: Luca Fedrizzi on X, https://twitter.com/lc_fd
Project-URL: Repository, https://github.com/lcfd/trak
Project-URL: Trak on X, https://twitter.com/usetrakcom
